[
  {
    "weapon": "m4a1-s",
    "skin-id": "Stratosphere"
  },
  {
    "weapon": "ak-47",
    "skin-id": "Midnight Laminate"
  },
  {
    "weapon": "usp-s",
    "skin-id": "Royal Guard"
  },
  {
    "weapon": "famas",
    "skin-id": "Yeti Camo"
  },
  {
    "weapon": "desert-eagle",
    "skin-id": "Mint Fan"
  },
  {
    "weapon": "p90",
    "skin-id": "Reef Grief"
  },
  {
    "weapon": "mp9",
    "skin-id": "Cobalt Paisley"
  },
  {
    "weapon": "p2000",
    "skin-id": "Royal Baroque"
  },
  {
    "weapon": "zeus-x27",
    "skin-id": "Electric Blue"
  },
  {
    "weapon": "glock-18",
    "skin-id": "Ocean Topo"
  },
  {
    "weapon": "m4a4",
    "skin-id": "Naval Shred Camo"
  },
  {
    "weapon": "negev",
    "skin-id": "Sour Grapes"
  },
  {
    "weapon": "xm1014",
    "skin-id": "Gum Wall Camo"
  },
  {
    "weapon": "galil-ar",
    "skin-id": "Robin's Egg"
  },
  {
    "weapon": "five-seven",
    "skin-id": "Sky Blue"
  },
  {
    "weapon": "nova",
    "skin-id": "Turquoise Pour"
  },
  {
    "weapon": "dual-berettas",
    "skin-id": "Rose Nacre"
  },
  {
    "weapon": "mp9",
    "skin-id": "Buff Blue"
  },
  {
    "weapon": "tec-9",
    "skin-id": "Blue Blast"
  },
  {
    "weapon": "galil-ar",
    "skin-id": "Grey Smoke"
  },
  {
    "weapon": "mp5-sd",
    "skin-id": "Lime Hex"
  },
  {
    "weapon": "p90",
    "skin-id": "Blue Tac"
  },
  {
    "weapon": "p250",
    "skin-id": "Plum Netting"
  },
  {
    "weapon": "mac-10",
    "skin-id": "Storm Camo"
  },
  {
    "weapon": "r8-revolver",
    "skin-id": "Cobalt Grip"
  },
  {
    "weapon": "ssg-08",
    "skin-id": "Grey Smoke"
  },
  {
    "weapon": "sg-553",
    "skin-id": "Night Camo"
  },
  {
    "weapon": "sawed-off",
    "skin-id": "Runoff"
  }
]